spatialsurf/__init__.py
spatialsurf/models/WTM.py
spatialsurf/models/__init__.py
spatialsurf/models/wae.py
spatialsurf/utils/__init__.py
spatialsurf/utils/calculate_cell_type_expression.py
spatialsurf/utils/cell_cell_communication.py
spatialsurf/utils/cell_type_matching.py
spatialsurf/utils/cell_type_visualization.py
spatialsurf/utils/data_pp.py
spatialsurf/utils/dataset.py
spatialsurf/utils/deconvolution.py
spatialsurf/utils/gene_set_enrichment_analysis.py
spatialsurf/utils/get_data_from_h5.py
spatialsurf/utils/identify_metagenes.py
spatialsurf/utils/pie_plot.py
spatialsurf-2.0.dist-info/licenses/LICENSE
spatialsurf-2.0.dist-info/METADATA
spatialsurf-2.0.dist-info/WHEEL
spatialsurf-2.0.dist-info/entry_points.txt
spatialsurf-2.0.dist-info/top_level.txt
spatialsurf-2.0.dist-info/RECORD
