Metadata-Version: 2.4
Name: spatialsurf
Version: 2.0
Summary: A self-supervised deep learning method for reference-free deconvolution.
Home-page: https://github.com/lllsssyyyy/SURF
Author: Shuyu Liang
Author-email: 
Classifier: Programming Language :: Python :: 3
Classifier: License :: OSI Approved :: MIT License
Classifier: Operating System :: OS Independent
License-File: LICENSE
Requires-Dist: pandas==1.5.3
Requires-Dist: numpy==1.23.0
Requires-Dist: scanpy==1.9.8
Requires-Dist: scipy==1.9.1
Requires-Dist: rpy2==3.6.1
Requires-Dist: tables
Requires-Dist: seaborn==0.13.2
Requires-Dist: matplotlib==3.7.1
Requires-Dist: pyarrow==14.0.1
Dynamic: author
Dynamic: classifier
Dynamic: description
Dynamic: description-content-type
Dynamic: home-page
Dynamic: license-file
Dynamic: requires-dist
Dynamic: summary
